{
  "id": "powersupplies-2-deepcool-pk550d-550w-bronze",
  "name": "DeepCool PK550D 550W Bronze",
  "brand": "DeepCool",
  "category": "Power Supplies",
  "price": 132000,
  "availability": "in_stock",
  "warranty": "1 Year Official Warranty",
  "image": "https://images.unsplash.com/photo-1591488320449-011701bb6704?auto=format&fit=crop&w=600&q=80",
  "specs": {
    "Wattage": "850W",
    "EfficiencyRating": "80 Plus Gold",
    "Modular": "Fully Modular",
    "Model": "DeepCool PK550D 550W Bronze"
  },
  "description": "Reliable power distributor with low heat output and high tolerance capacitors.",
  "highlights": [
    "Genuine factory certified product",
    "Official warranty distribution in Pakistan",
    "High performance design and build",
    "Full support via WhatsApp chat"
  ]
}