{
  "id": "rtx-4090-price-in-pakistan",
  "name": "ASUS ROG Strix GeForce RTX 4090 OC Edition Graphics Card",
  "brand": "Asus",
  "category": "Graphics Cards",
  "availability": "out_of_stock",
  "warranty": "Official Brand Warranty",
  "image": "https://redtech.pk/wp-content/uploads/2024/08/ASUS-ROG-Strix-GeForce-RTX-4090-OC-Edition-Gaming-PCIe-4.0-24GB-GDDR6X-HDMI-2.1a-DisplayPort-1.4a-Graphics-Card-Price-in-Pakistan.jpg",
  "highlights": [
    "16384 CUDA Cores",
    "24GB GDDR6X 384-bit Memory",
    "Boost Clock Up to 2640 MHz (OC Mode)",
    "PCIe 4.0 Ultra Performance Interface",
    "ARGB Aura Sync Lighting Support"
  ],
  "description": "ASUS ROG Strix GeForce RTX 4090 OC Edition Graphics Card What is ASUS ROG Strix GeForce RTX 4090 OC Edition Graphics Card price in Pakistan? ASUS ROG Strix GeForce RTX 4090 OC Edition Graphics Card price in Pakistan is Rs.735,000. It features the NVIDIA RTX 4090 GPU with 16384 CUDA cores and 24GB GDDR6X memory on a 384-bit bus for extreme 4K and AI performance. With PCIe 4.0 interface, HDMI 2.1a and DisplayPort 1.4a outputs, it delivers top-tier ray tracing and gaming power. Buy genuine premium "
}