{
  "id": "ryzen-9-9950x-price-in-pakistan",
  "name": "AMD Ryzen 9 9950X Processor",
  "brand": "Ryzen",
  "category": "Processors",
  "availability": "in_stock",
  "warranty": "Official Brand Warranty",
  "image": "https://redtech.pk/wp-content/uploads/2026/06/rbtech_amd_ryzen_9_9950x-510x510-1.jpg",
  "highlights": [
    "The AMD Ryzen 9 9950X is a 16 core, 32 thread Zen 5 processor built for gamers, creators and professionals who demand top tier performance",
    "With a base clock of 4",
    "3GHz boosting up to 5",
    "7GHz and 64MB of L3 cache, it handles heavy multitasking and gaming with ease"
  ],
  "description": "Ryzen 9 9950X Price in Pakistan If you are looking for the Ryzen 9 9950X price in Pakistan, Red Tech Gaming Store brings you this flagship 16 core, 32 thread Zen 5 processor built for gamers, creators and professionals who refuse to compromise. With boost speeds reaching 5.7GHz on the AM5 platform, it delivers desktop level performance for even the most demanding workloads. For the latest pricing and stock availability, feel free to reach out on WhatsApp and our team will assist you right away. "
}