{
  "id": "silverstone-da1000r-cybenetics-gold-sst-da1000r-gm-1000w-atx-3-0-pcie-5-0-fully-modular-atx-power-supply",
  "name": "SilverStone DA1000R Cybenetics Gold  SST-DA1000R-GM 1000W ATX 3.0 &#038; PCIe 5.0 Fully Modular ATX Power Supply",
  "brand": "Silverstone",
  "category": "Power Supplies",
  "availability": "out_of_stock",
  "warranty": "Official Brand Warranty",
  "image": "https://redtech.pk/wp-content/uploads/2024/08/da1000r-gm-23.jpg",
  "highlights": [
    "Equipped with Gen5 12VHPWR PCIe connector, meeting Intel ATX 3.0 specification standard",
    "Cybenetics Gold efficiency certification",
    "24/7 continuous power output with 50℃operating temperature",
    "Fully Modular design",
    "All Japanese electrolytic capacitors"
  ],
  "description": "SilverStone SST-DA1000R-GM DA1000R Cybenetics Gold 1000W ATX 3.0 &amp; PCIe 5.0 Fully Modular ATX Power Supply Price in Pakistan"
}